inspector_django/__init__.py
inspector_django/middleware.py
inspector_django/enums/__init__.py
inspector_django/enums/settings_enum.py
inspector_django/lib/__init__.py
inspector_django/lib/app_configurations.py
inspector_django/lib/inspector_django.py
inspector_django/tracking/__init__.py
inspector_django/tracking/guard_transaction.py
inspector_django/tracking/sql_hook.py
inspector_django-0.1.3.dist-info/LICENSE
inspector_django-0.1.3.dist-info/METADATA
inspector_django-0.1.3.dist-info/WHEEL
inspector_django-0.1.3.dist-info/top_level.txt
inspector_django-0.1.3.dist-info/RECORD
