Metadata-Version: 2.1
Name: inspector-django
Version: 0.1.3
Summary: Real-time Code Execution Monitoring of your Django applications.
Home-page: https://inspector.dev/
Author: Inspector
Author-email: support@inspector.dev
License: MIT
Project-URL: Documentation, https://docs.inspector.dev/guides/django/
Project-URL: Source Code, https://github.com/inspector-apm/inspector-django
Project-URL: Issue Tracker, https://github.com/inspector-apm/inspector-django/issues
License-File: LICENSE
Requires-Dist: Django (>=3)
Requires-Dist: inspector-python
Provides-Extra: tests
Requires-Dist: pytest ; extra == 'tests'
